quickner-0.0.1a20.dist-info/METADATA
quickner-0.0.1a20.dist-info/WHEEL
quickner-0.0.1a20.dist-info/entry_points.txt
quickner-0.0.1a20.dist-info/license_files/LICENSE
quickner/__init__.py
quickner/__init__.pyi
quickner/py.typed
quickner/quickner.cp311-win_amd64.pyd
quickner-0.0.1a20.dist-info/RECORD
