Metadata-Version: 2.1
Name: quickner
Version: 0.0.1a20
Classifier: Programming Language :: Rust
Classifier: Programming Language :: Python :: Implementation :: CPython
Classifier: Programming Language :: Python :: Implementation :: PyPy
License-File: LICENSE
Summary: A fast and simple NER tool
Keywords: ner,named-entity-recognition,nlp,natural-language-processing
Author: Omar MHAIMDAT
License: Mozilla Public License 2.0
Requires-Python: >=3.6
